{
  "generated_at": "2026-05-02T08:12:04.220Z",
  "source": {
    "type": "github_actions_artifacts",
    "repo": "runxhq/aster",
    "artifact_prefixes": [
      "issue-triage-",
      "skill-lab-"
    ],
    "artifact_limit": 200
  },
  "stats": {
    "tracked_artifacts": 7,
    "newly_processed_artifacts": 7,
    "applied_summaries": 5,
    "suppressed_summaries": 2,
    "skipped_artifacts": 30,
    "errors": 0
  },
  "artifacts": [
    {
      "artifact_id": 6593112868,
      "name": "issue-triage-pr-116",
      "created_at": "2026-04-23T03:02:07Z",
      "updated_at": "2026-04-23T03:02:07Z",
      "workflow_run_id": 24814325912,
      "head_branch": "main",
      "head_sha": "c2ebcbf863524870bd8e290b58acdb9de641dc26",
      "summaries": [
        {
          "lane": "issue-triage",
          "status": "success",
          "receipt_id": "rx_51a23b4368004a7d9dc65198463e4abe",
          "summary": "lane finished with success",
          "packet_created_at": "2026-04-23T03:02:06.118Z",
          "subject_locator": "nilstate/aster#pr/116",
          "target_repo": "nilstate/aster",
          "objective_fingerprint": "6790d0b4cd0f3062bb2e67f34511b5175f91c2d8",
          "projection_key": "issue-triage::nilstate/aster#pr/116::6790d0b4cd0f3062bb2e67f34511b5175f91c2d8",
          "reflection_path": "reflections/2026-04-23-issue-triage-nilstate-aster-pr-116-lane-finished-with-success.md",
          "history_path": "history/2026-04-23-issue-triage-nilstate-aster-pr-116-lane-finished-with-success.md",
          "target_dossier_path": "state/targets/nilstate-aster.md",
          "promotion_scope": "public",
          "public_projection_reasons": [
            "objective_fingerprint"
          ]
        }
      ]
    },
    {
      "artifact_id": 6593240254,
      "name": "skill-lab-115",
      "created_at": "2026-04-23T03:13:48Z",
      "updated_at": "2026-04-23T03:13:48Z",
      "workflow_run_id": 24814535068,
      "head_branch": "main",
      "head_sha": "51bc4577cc4b24072723320d817cd9e278aad95d",
      "summaries": [
        {
          "lane": "skill-lab",
          "status": "success",
          "receipt_id": "rx_4038071dc524433ca20aab91fff4d578",
          "summary": "Read one living work ledger plus trusted amendments and return one bounded maintainer decision packet for review.",
          "packet_created_at": "2026-04-23T03:13:28.627Z",
          "subject_locator": "nilstate/aster#issue/115",
          "target_repo": "nilstate/aster",
          "objective_fingerprint": null,
          "projection_key": "skill-lab::nilstate/aster#issue/115",
          "reflection_path": "reflections/2026-04-23-skill-lab-nilstate-aster-issue-115-read-one-living-work-ledger-plus-trusted-amendme.md",
          "history_path": "history/2026-04-23-skill-lab-nilstate-aster-issue-115-read-one-living-work-ledger-plus-trusted-amendme.md",
          "target_dossier_path": "state/targets/nilstate-aster.md",
          "promotion_scope": "public",
          "public_projection_reasons": [
            "durable_summary"
          ]
        }
      ]
    },
    {
      "artifact_id": 6593321756,
      "name": "skill-lab-115",
      "created_at": "2026-04-23T03:21:26Z",
      "updated_at": "2026-04-23T03:21:26Z",
      "workflow_run_id": 24814783013,
      "head_branch": "main",
      "head_sha": "a63971dd4138b1fc06a47a187c38b54dc6b8b3b1",
      "summaries": [
        {
          "lane": "skill-lab",
          "status": "success",
          "receipt_id": "rx_4dbfd5b61c8340a192e0757b253171b1",
          "summary": "Read one living work ledger and return one bounded decision packet for the next human step.",
          "packet_created_at": "2026-04-23T03:21:08.069Z",
          "subject_locator": "nilstate/aster#issue/115",
          "target_repo": "nilstate/aster",
          "objective_fingerprint": null,
          "projection_key": "skill-lab::nilstate/aster#issue/115",
          "reflection_path": "reflections/2026-04-23-skill-lab-nilstate-aster-issue-115-read-one-living-work-ledger-and-return-one-bound.md",
          "history_path": "history/2026-04-23-skill-lab-nilstate-aster-issue-115-read-one-living-work-ledger-and-return-one-bound.md",
          "target_dossier_path": "state/targets/nilstate-aster.md",
          "promotion_scope": "public",
          "public_projection_reasons": [
            "durable_summary"
          ]
        }
      ]
    },
    {
      "artifact_id": 6593334039,
      "name": "issue-triage-pr-116",
      "created_at": "2026-04-23T03:22:41Z",
      "updated_at": "2026-04-23T03:22:41Z",
      "workflow_run_id": 24814908855,
      "head_branch": "main",
      "head_sha": "a63971dd4138b1fc06a47a187c38b54dc6b8b3b1",
      "summaries": [
        {
          "lane": "issue-triage",
          "status": "success",
          "receipt_id": "rx_1a8531a162214642b8b526b1db417488",
          "summary": "lane finished with success",
          "packet_created_at": "2026-04-23T03:22:40.033Z",
          "subject_locator": "nilstate/aster#pr/116",
          "target_repo": "nilstate/aster",
          "objective_fingerprint": "a8e478ec2f3841c59134a0567ea87179e532c6cf",
          "projection_key": "issue-triage::nilstate/aster#pr/116::a8e478ec2f3841c59134a0567ea87179e532c6cf",
          "reflection_path": "reflections/2026-04-23-issue-triage-nilstate-aster-pr-116-lane-finished-with-success.md",
          "history_path": "history/2026-04-23-issue-triage-nilstate-aster-pr-116-lane-finished-with-success.md",
          "target_dossier_path": "state/targets/nilstate-aster.md",
          "promotion_scope": "public",
          "public_projection_reasons": [
            "objective_fingerprint"
          ]
        }
      ]
    },
    {
      "artifact_id": 6593393769,
      "name": "skill-lab-115",
      "created_at": "2026-04-23T03:29:00Z",
      "updated_at": "2026-04-23T03:29:00Z",
      "workflow_run_id": 24814974331,
      "head_branch": "main",
      "head_sha": "4b24e073b61e1f7dd9e19445d442a107c4a975b8",
      "summaries": [
        {
          "lane": "skill-lab",
          "status": "success",
          "receipt_id": "rx_ae7f11f40d7e4074bc93d078798bf4ca",
          "summary": "Read one living work ledger plus trusted amendments and return one bounded maintainer decision packet.",
          "packet_created_at": "2026-04-23T03:28:38.921Z",
          "subject_locator": "nilstate/aster#issue/115",
          "target_repo": "nilstate/aster",
          "objective_fingerprint": null,
          "projection_key": "skill-lab::nilstate/aster#issue/115",
          "reflection_path": "reflections/2026-04-23-skill-lab-nilstate-aster-issue-115-read-one-living-work-ledger-plus-trusted-amendme.md",
          "history_path": "history/2026-04-23-skill-lab-nilstate-aster-issue-115-read-one-living-work-ledger-plus-trusted-amendme.md",
          "target_dossier_path": "state/targets/nilstate-aster.md",
          "promotion_scope": "public",
          "public_projection_reasons": [
            "durable_summary"
          ]
        }
      ]
    },
    {
      "artifact_id": 6593407463,
      "name": "issue-triage-pr-116",
      "created_at": "2026-04-23T03:30:35Z",
      "updated_at": "2026-04-23T03:30:35Z",
      "workflow_run_id": 24815114485,
      "head_branch": "main",
      "head_sha": "4b24e073b61e1f7dd9e19445d442a107c4a975b8",
      "summaries": [
        {
          "lane": "issue-triage",
          "status": "success",
          "receipt_id": "rx_9e6be621a4204349a65661f3f1cfc591",
          "summary": "lane finished with success",
          "packet_created_at": "2026-04-23T03:30:34.645Z",
          "subject_locator": "nilstate/aster#pr/116",
          "target_repo": "nilstate/aster",
          "objective_fingerprint": "7554406e75305df1b10576ef998b4458aed6d425",
          "projection_key": "issue-triage::nilstate/aster#pr/116::7554406e75305df1b10576ef998b4458aed6d425",
          "reflection_path": "reflections/2026-04-23-issue-triage-nilstate-aster-pr-116-lane-finished-with-success.md",
          "history_path": "history/2026-04-23-issue-triage-nilstate-aster-pr-116-lane-finished-with-success.md",
          "target_dossier_path": "state/targets/nilstate-aster.md",
          "promotion_scope": "public",
          "public_projection_reasons": [
            "objective_fingerprint"
          ]
        }
      ]
    },
    {
      "artifact_id": 6593968076,
      "name": "issue-triage-pr-117",
      "created_at": "2026-04-23T04:31:20Z",
      "updated_at": "2026-04-23T04:31:20Z",
      "workflow_run_id": 24816812633,
      "head_branch": "runx/thread-teaching-derive-24816652074",
      "head_sha": "9bd2771d0f6608550af496b8d832f160ecad3dcf",
      "summaries": [
        {
          "lane": "issue-triage",
          "status": "success",
          "receipt_id": "rx_bd599663a9404515adbc05f48c92ec74",
          "summary": "lane finished with success",
          "packet_created_at": "2026-04-23T04:31:19.156Z",
          "subject_locator": "nilstate/aster#pr/117",
          "target_repo": "nilstate/aster",
          "objective_fingerprint": "9bd2771d0f6608550af496b8d832f160ecad3dcf",
          "projection_key": "issue-triage::nilstate/aster#pr/117::9bd2771d0f6608550af496b8d832f160ecad3dcf",
          "reflection_path": "reflections/2026-04-23-issue-triage-nilstate-aster-pr-117-lane-finished-with-success.md",
          "history_path": "history/2026-04-23-issue-triage-nilstate-aster-pr-117-lane-finished-with-success.md",
          "target_dossier_path": "state/targets/nilstate-aster.md",
          "promotion_scope": "public",
          "public_projection_reasons": [
            "objective_fingerprint"
          ]
        }
      ]
    }
  ],
  "projection_groups": [
    {
      "projection_key": "issue-triage::nilstate/aster#pr/116::6790d0b4cd0f3062bb2e67f34511b5175f91c2d8",
      "lane": "issue-triage",
      "subject_locator": "nilstate/aster#pr/116",
      "target_repo": "nilstate/aster",
      "objective_fingerprint": "6790d0b4cd0f3062bb2e67f34511b5175f91c2d8",
      "selected_artifact_id": 6593112868,
      "selected_receipt_id": "rx_51a23b4368004a7d9dc65198463e4abe",
      "selected_summary": "lane finished with success",
      "selected_promotion_scope": "public",
      "public_selected_artifact_id": 6593112868,
      "public_selected_receipt_id": "rx_51a23b4368004a7d9dc65198463e4abe",
      "public_selected_summary": "lane finished with success",
      "public_selected_promotion_scope": "public",
      "public_projection_reasons": [
        "objective_fingerprint"
      ],
      "suppressed_artifact_ids": []
    },
    {
      "projection_key": "issue-triage::nilstate/aster#pr/116::7554406e75305df1b10576ef998b4458aed6d425",
      "lane": "issue-triage",
      "subject_locator": "nilstate/aster#pr/116",
      "target_repo": "nilstate/aster",
      "objective_fingerprint": "7554406e75305df1b10576ef998b4458aed6d425",
      "selected_artifact_id": 6593407463,
      "selected_receipt_id": "rx_9e6be621a4204349a65661f3f1cfc591",
      "selected_summary": "lane finished with success",
      "selected_promotion_scope": "public",
      "public_selected_artifact_id": 6593407463,
      "public_selected_receipt_id": "rx_9e6be621a4204349a65661f3f1cfc591",
      "public_selected_summary": "lane finished with success",
      "public_selected_promotion_scope": "public",
      "public_projection_reasons": [
        "objective_fingerprint"
      ],
      "suppressed_artifact_ids": []
    },
    {
      "projection_key": "issue-triage::nilstate/aster#pr/116::a8e478ec2f3841c59134a0567ea87179e532c6cf",
      "lane": "issue-triage",
      "subject_locator": "nilstate/aster#pr/116",
      "target_repo": "nilstate/aster",
      "objective_fingerprint": "a8e478ec2f3841c59134a0567ea87179e532c6cf",
      "selected_artifact_id": 6593334039,
      "selected_receipt_id": "rx_1a8531a162214642b8b526b1db417488",
      "selected_summary": "lane finished with success",
      "selected_promotion_scope": "public",
      "public_selected_artifact_id": 6593334039,
      "public_selected_receipt_id": "rx_1a8531a162214642b8b526b1db417488",
      "public_selected_summary": "lane finished with success",
      "public_selected_promotion_scope": "public",
      "public_projection_reasons": [
        "objective_fingerprint"
      ],
      "suppressed_artifact_ids": []
    },
    {
      "projection_key": "issue-triage::nilstate/aster#pr/117::9bd2771d0f6608550af496b8d832f160ecad3dcf",
      "lane": "issue-triage",
      "subject_locator": "nilstate/aster#pr/117",
      "target_repo": "nilstate/aster",
      "objective_fingerprint": "9bd2771d0f6608550af496b8d832f160ecad3dcf",
      "selected_artifact_id": 6593968076,
      "selected_receipt_id": "rx_bd599663a9404515adbc05f48c92ec74",
      "selected_summary": "lane finished with success",
      "selected_promotion_scope": "public",
      "public_selected_artifact_id": 6593968076,
      "public_selected_receipt_id": "rx_bd599663a9404515adbc05f48c92ec74",
      "public_selected_summary": "lane finished with success",
      "public_selected_promotion_scope": "public",
      "public_projection_reasons": [
        "objective_fingerprint"
      ],
      "suppressed_artifact_ids": []
    },
    {
      "projection_key": "skill-lab::nilstate/aster#issue/115",
      "lane": "skill-lab",
      "subject_locator": "nilstate/aster#issue/115",
      "target_repo": "nilstate/aster",
      "objective_fingerprint": null,
      "selected_artifact_id": 6593393769,
      "selected_receipt_id": "rx_ae7f11f40d7e4074bc93d078798bf4ca",
      "selected_summary": "Read one living work ledger plus trusted amendments and return one bounded maintainer decision packet.",
      "selected_promotion_scope": "public",
      "public_selected_artifact_id": 6593393769,
      "public_selected_receipt_id": "rx_ae7f11f40d7e4074bc93d078798bf4ca",
      "public_selected_summary": "Read one living work ledger plus trusted amendments and return one bounded maintainer decision packet.",
      "public_selected_promotion_scope": "public",
      "public_projection_reasons": [
        "durable_summary"
      ],
      "suppressed_artifact_ids": [
        6593321756,
        6593240254
      ]
    }
  ]
}
